nikita_probability/Binomialdistribution.py
nikita_probability/Gaussiandistribution.py
nikita_probability/Generaldistribution.py
nikita_probability/__init__.py
nikita_probability-0.1.dist-info/DESCRIPTION.rst
nikita_probability-0.1.dist-info/METADATA
nikita_probability-0.1.dist-info/RECORD
nikita_probability-0.1.dist-info/WHEEL
nikita_probability-0.1.dist-info/metadata.json
nikita_probability-0.1.dist-info/top_level.txt
